pareqs/__init__.py
pareqs/pareqs.py
pareqs/models/__init__.py
pareqs/models/pares.py
pareqs-0.1.0.dist-info/METADATA
pareqs-0.1.0.dist-info/WHEEL
pareqs-0.1.0.dist-info/top_level.txt
pareqs-0.1.0.dist-info/RECORD
