Metadata-Version: 2.1
Name: pareqs
Version: 0.1.0
Summary: Tool to decode PaReq and PaRes into handy Python objects
Home-page: https://gitlab.com/whiteapfel/pareqs
Author: WhiteApfel
Author-email: white@pfel.ru
License: Mozilla Public License 2.0
Project-URL: Donate, https://pfel.cc/donate
Project-URL: Source, https://github.com/WhiteApfel/pyQiwiP2P
Project-URL: Telegram, https://t.me/apfel
Keywords: payments 3ds threedsecure pareq pares
Platform: UNKNOWN
Requires-Dist: pytest (~=6.2.2)
Requires-Dist: xsdata (~=21.6)
